EasIlastik/__init__.py
EasIlastik/find_ilastik.py
EasIlastik/run_ilastik.py
EasIlastik/utils.py
EasIlastik-1.0.2.dist-info/LICENCE
EasIlastik-1.0.2.dist-info/METADATA
EasIlastik-1.0.2.dist-info/README.md
EasIlastik-1.0.2.dist-info/WHEEL
EasIlastik-1.0.2.dist-info/top_level.txt
EasIlastik-1.0.2.dist-info/RECORD
