Metadata-Version: 2.1
Name: EasIlastik
Version: 1.0.2
Summary: This package provides seamless integration of pre-trained image segmentation models from Ilastik into Python workflows, empowering users with efficient and intuitive image segmentation capabilities for diverse applications.
Home-page: https://github.com/titouanlegourrierec/EasIlastik
Author: Titouan Le Gourrierec
Author-email: titouanlegourrierec@icloud.com
License: GPLv3
Keywords: ilastik image-segmentation machine-learning python image
Classifier: License :: OSI Approved :: GNU General Public License v3 (GPLv3)
Classifier: Programming Language :: Python :: 3
Classifier: Programming Language :: Python :: 3.6
Classifier: Programming Language :: Python :: 3.7
Classifier: Programming Language :: Python :: 3.8
Classifier: Programming Language :: Python :: 3.9
Classifier: Programming Language :: Python :: 3.10
Classifier: Operating System :: OS Independent
Classifier: Intended Audience :: Science/Research
Requires-Python: >=3.6
License-File: LICENCE
Requires-Dist: numpy
Requires-Dist: h5py
Requires-Dist: opencv-python
